MANIFEST.in
README.rst
setup.py
django_menu.egg-info/PKG-INFO
django_menu.egg-info/SOURCES.txt
django_menu.egg-info/dependency_links.txt
django_menu.egg-info/not-zip-safe
django_menu.egg-info/requires.txt
django_menu.egg-info/top_level.txt
menu/__init__.py
menu/admin.py
menu/models.py
menu/views.py
menu/migrations/0001_initial.py
menu/migrations/0002_auto__add_field_menuitem_anonymous_only.py
menu/migrations/__init__.py
menu/templatetags/__init__.py
menu/templatetags/menubuilder.py