Metadata-Version: 1.0
Name: django-menu
Version: 0.1.7
Summary: Django-powered website navigation maintenance tool
Home-page: http://github.com/rossp/django-menu
Author: Ross Poulton
Author-email: ross@rossp.org
License: BSD
Keywords: django,menus,navigatino
Platform: UNKNOWN
Classifier: Programming Language :: Python
Classifier: Topic :: Software Development :: Libraries :: Python Modules
Classifier: Framework :: Django
Classifier: Environment :: Web Environment
Classifier: Operating System :: OS Independent
Classifier: License :: OSI Approved :: BSD License
Classifier: Natural Language :: English
